blipacmanager/__init__.py
blipacmanager/acmanager.py
blipacmanager/remove.py
blipacmanager-0.0.3.dist-info/LICENSE.txt
blipacmanager-0.0.3.dist-info/METADATA
blipacmanager-0.0.3.dist-info/WHEEL
blipacmanager-0.0.3.dist-info/RECORD
