Metadata-Version: 2.1
Name: blipacmanager
Version: 0.0.3
Summary: Manipulação das combinações do Assistente de Conteudo.
Author: Caio Souza
Author-email: caios@blip.ai
Requires-Python: >=3.6
Classifier: Development Status :: 4 - Beta
Classifier: License :: OSI Approved :: MIT License
Classifier: Operating System :: OS Independent
Classifier: Programming Language :: Python :: 3
Classifier: Programming Language :: Python :: 3.6
Classifier: Programming Language :: Python :: 3.7
Classifier: Programming Language :: Python :: 3.8
Classifier: Programming Language :: Python :: 3.9
Classifier: Programming Language :: Python :: 3.10
Classifier: Programming Language :: Python :: 3.11
Requires-Dist: pandas (>=1.3.0)
Requires-Dist: requests (>=2.26.0,<3.0.0)
Requires-Dist: ujson (>=4.2.0,<5.0.0)
Requires-Dist: unidecode (>=1.0.0)
